shopline_qa_util/__init__.py
shopline_qa_util/db_util.py
shopline_qa_util-0.0.6.dist-info/LICENSE
shopline_qa_util-0.0.6.dist-info/METADATA
shopline_qa_util-0.0.6.dist-info/WHEEL
shopline_qa_util-0.0.6.dist-info/top_level.txt
shopline_qa_util-0.0.6.dist-info/RECORD
