Metadata-Version: 2.1
Name: shopline-qa-util
Version: 0.0.6
Summary: shopline qa util
Home-page: https://shoplineapp.cn
Author: zhouibhui
Author-email: zhoubihui@shoplineapp.com
License: MIT
Platform: all
Classifier: Operating System :: OS Independent
Classifier: Programming Language :: Python :: 3
Classifier: License :: OSI Approved :: MIT License
License-File: LICENSE
Requires-Dist: requests (>=2.24.0)
